LICENSE.md
MANIFEST.in
README.md
setup.py
dsf_cli.egg-info/PKG-INFO
dsf_cli.egg-info/SOURCES.txt
dsf_cli.egg-info/dependency_links.txt
dsf_cli.egg-info/entry_points.txt
dsf_cli.egg-info/requires.txt
dsf_cli.egg-info/top_level.txt
dsfcli/__init__.py
dsfcli/__main__.py
dsfcli/CloudAccount/README.md
dsfcli/CloudAccount/__init__.py
dsfcli/CloudAccount/cloud_crud.py
dsfcli/CloudAccount/cloud_scheduler_operations.py
dsfcli/DataSources/README.md
dsfcli/DataSources/__init__.py
dsfcli/DataSources/data_source_crud.py
dsfcli/DataSources/data_source_scheduler_operations.py
dsfcli/Gateways/README.md
dsfcli/Gateways/__init__.py
dsfcli/GeneralAssets/README.md
dsfcli/GeneralAssets/__init__.py
dsfcli/GeneralAssets/general_crud.py
dsfcli/GeneralAssets/general_operations.py
dsfcli/LogAggregator/README.md
dsfcli/LogAggregator/__init__.py
dsfcli/LogAggregator/log_agg_crud.py
dsfcli/LogAggregator/log_agg_scheduler_operations.py
dsfcli/SecretManager/README.md
dsfcli/SecretManager/__init__.py
dsfcli/SecretManager/secret_manager_crud.py
dsfcli/SecretManager/secret_manager_operations.py
dsfcli/Utils/clidriver.py
scripts/dsflib.py
scripts/process_data_source_metadata.py
scripts/swaggerLib.py
swagger_client/__init__.py
swagger_client/api_client.py
swagger_client/configuration.py
swagger_client/rest.py
swagger_client/api/__init__.py
swagger_client/api/cloud_accounts_api.py
swagger_client/api/data_sources_api.py
swagger_client/api/gateways_api.py
swagger_client/api/general_assets_api.py
swagger_client/api/log_aggregators_api.py
swagger_client/api/secret_managers_api.py
swagger_client/models/__init__.py
swagger_client/models/api_data_asset_dto.py
swagger_client/models/api_data_discovery_request_dto.py
swagger_client/models/api_data_schedule_item_dto.py
swagger_client/models/discovery_request_dto.py
swagger_client/models/no_schema.py
swagger_client/models/schedule_item_dto.py