Metadata-Version: 2.1
Name: dsf-cli
Version: 1.0.28
Summary: CLI for gateway, asset CRUD on DSF via API.
Home-page: https://github.com/imperva/dsf-cli
Author: Joe Moore
Author-email: joe.moore@imperva.com
License: Imperva-Community Developer License
Classifier: License :: OSI Approved :: MIT License
Classifier: Programming Language :: Python :: 3.6
Classifier: Programming Language :: Python :: 3.7
Classifier: Programming Language :: Python :: 3.8
Classifier: Programming Language :: Python :: 3.9
Requires-Python: >=3.6
License-File: LICENSE.md
Requires-Dist: urllib3
Requires-Dist: certifi
Requires-Dist: six
